aicontext/__init__.py
aicontext/core.py
aicontext-0.0.1.dist-info/METADATA
aicontext-0.0.1.dist-info/WHEEL
aicontext-0.0.1.dist-info/RECORD
