Metadata-Version: 2.1
Name: aicontext
Version: 0.0.1
Summary: Simple context management for AI conversations
Home-page: https://github.com/spencerkinney/aicontext
License: MIT
Keywords: ai,chat,context,llm,conversation
Author: Spencer Kinney
Author-email: email@spencerkinney.dev
Requires-Python: >=3.8,<3.14
Classifier: Development Status :: 4 - Beta
Classifier: Intended Audience :: Developers
Classifier: License :: OSI Approved :: MIT License
Classifier: Programming Language :: Python :: 3
Classifier: Programming Language :: Python :: 3.8
Classifier: Programming Language :: Python :: 3.9
Classifier: Programming Language :: Python :: 3.10
Classifier: Programming Language :: Python :: 3.11
Classifier: Programming Language :: Python :: 3.12
Classifier: Programming Language :: Python :: 3.13
Classifier: Topic :: Scientific/Engineering :: Artificial Intelligence
Classifier: Topic :: Software Development :: Libraries :: Python Modules
Requires-Dist: typing-extensions (>=4.9.0,<5.0.0)
Project-URL: Repository, https://github.com/spencerkinney/aicontext
